{
  "$schema": "https://developer.microsoft.com/json-schemas/spfx-build/package-solution.schema.json",
  "solution": {
    "name": "spfx-pn-p-client-side-solution",
    "id": "68a5a210-78c8-45cf-b04c-5b0c25e3342a",
    "version": "1.0.0.0",
    "includeClientSideAssets": true,
    "skipFeatureDeployment": true,
    "isDomainIsolated": false,
    "developer": {
      "name": "",
      "websiteUrl": "",
      "privacyUrl": "",
      "termsOfUseUrl": "",
      "mpnId": "Undefined-1.16.1"
    },
    "metadata": {
      "shortDescription": {
        "default": "spfx-pn-p description"
      },
      "longDescription": {
        "default": "spfx-pn-p description"
      },
      "screenshotPaths": [],
      "videoUrl": "",
      "categories": []
    },
    "features": [
      {
        "title": "spfx-pn-p Feature",
        "description": "The feature that activates elements of the spfx-pn-p solution.",
        "id": "bd87b204-a42d-46a9-a06b-d371b00beb7d",
        "version": "1.0.0.0"
      }
    ]
  },
  "paths": {
    "zippedPackage": "solution/spfx-pn-p.sppkg"
  }
}
